<?xml version="1.0" encoding="utf-8"?>
<odoo>
    <record id="product_brand_form_inherit" model="ir.ui.view">
        <field name="name">product.brand.form.inherit</field>
        <field name="model">product.brand</field>
        <field name="inherit_id" ref="product_brand.view_product_brand_form"/>
        <field name="arch" type="xml">
            <field name="company_type" position="after">
                <field name="is_discontinued"/>
            </field>
        </field>
    </record>
</odoo>