<odoo>
	<data>
		<record id="redeem_point_wizard_form" model="ir.ui.view">
			<field name="name">reedem_loyalty_form_wizard</field>
			<field name="model">loyalty.wizard.reedem</field>
			<field name="type">form</field>
			<field name="arch" type="xml">        
				<form string="Loyalty Reedmption ">
					<sheet>
					   <group>
							<field name="customer"/>
							<field name="loyalty_point"/>
							<field name="loyalty_balance"/>
							<field name="redeem_point" placeholder="Enter Point to Redeem"/>
					   </group>
						<footer>                        
							<button name="ok_redeem" string="Redeem" type="object" class="btn-primary"/>    
						</footer>                    
					</sheet>                   
				</form>
			</field>
		</record>

		<record id="redeem_point_wizard" model="ir.actions.act_window">
			<field name="name">Loyalty Reedmption</field>
			<field name="type">ir.actions.act_window</field>
			<field name="res_model">loyalty.wizard.reedem</field>           
			<field name="view_mode">form</field>          
			<field name="target">new</field>
		</record>
		
		<record id="loyalty_form_inherit_sale" model="ir.ui.view">
				<field name="name">loyalty.form.inherit.sale</field>
				<field name="model">sale.order</field>
				<field name="inherit_id" ref="sale.view_order_form"/>
				<field name="arch" type="xml">
					<xpath expr="//button[@name='action_cancel']" position="after">
						<field name="is_from_website" invisible="1"/>
						<button name="%(bi_loyalty_generic.redeem_point_wizard)d"  type="action" string="Redeem" class="oe_highlight"
							attrs="{'invisible': ['|',('is_from_website','=',True),('state','!=','draft')]}"/>
					</xpath>
				</field>
		</record>      

	</data>
</odoo>
